<?xml version="1.0" encoding="UTF-8"?>
<gibo>
	<gseq>18906</gseq><!-- 기보 시퀀스 -->
	<playdate>2009-04-11</playdate>	<!-- 대국일자 (YYYYMMDD)-->
	<kind>0</kind>	<!-- 구분(1:프로기보, 2:한게임기보) -->
	<title>
				
				[제22회 후지쯔배] 본선1회전
				
			
	</title> <!-- 기보 제목(기전이름/상태 입력 상태에 따라 가공하여 보냄) -->
	<playerbseq>67</playerbseq>		<!-- 흑대국자 시퀀스 (=badukpeople.seq)-->
	<playerbname>원성진</playerbname>		<!-- 흑대국자 이름 (=badukpeople.namekorean)-->
	<playerbgrade>9단</playerbgrade>	<!-- 흑대국자 단수 (기보 입력당시의 단수)-->
	<playerbimg>
		http://badukwww.hangame.com/2008baduk/pro_photo/pro_photo123.jpg
		
	</playerbimg>		<!-- 흑대국자 썸네일(입력 안된 경우 노이미지 URL로 보냄) -->
	<playerwseq>453</playerwseq>		<!-- 백대국자 시퀀스 (=badukpeople.seq)-->
	<playerwname>이야마 유타 </playerwname>		<!-- 백대국자 이름 (=badukpeople.namekorean)-->
	<playerwgrade>8단</playerwgrade>	<!-- 백대국자 단수 (기보 입력당시의 단수)-->
	<playerwimg>
		http://badukwww.hangame.com/2008baduk/pro_photo/japan/pro_photo147.jpg
		
	</playerwimg>		<!-- 백대국자 썸네일(입력 안된 경우 노이미지 URL로 보냄)-->
	<winplayerseq>453</winplayerseq>	<!-- 승자 시퀀스 (=badukpeople.seq)-->
	<defeatplayerseq>67</defeatplayerseq>	<!-- 패자 시퀀스 (=badukpeople.seq)-->
	<extra>6.5</extra>			<!-- 덤-->
	<gomi>호선</gomi>			<!-- 치수-->
	<limittime>3시간 60초 10회</limittime>		<!-- 제한시간-->
	<place>일본 도쿄</place>			<!-- 대국장소-->
	<result>백 불계승</result>	<!-- 결과(ex: 흑 불계승)-->
	<readnum>461</readnum>		<!-- 조회수-->
	<gibodata>(;AP[PureMorph:1.0]CA[ISO-2022-KR]FF[4]GM[1]ST[2]SZ[19]GN[]PC[http://www.hangame.com/]DT[]TS[]TF[]TM[3시간60초10회]RE[백 불계승]HA[호선 - 6집 반 공제]HH[1]PW[[p]이야마]PB[[p]원성진]WR[209]BR[209]ZC[]ZT[]AN[]HC[0]VW[aa:ss]QT[60]QC[5]QF[0]N[Title]C[Summary]QK[DMessage];B[pd]QM[0]N[정답도]C[--]QA[];W[dd];B[qp];W[dq];B[oq];W[qj];B[co];W[qg];B[nc];W[ck];B[ep];W[eq];B[fp];W[gq];B[cq];W[dp];B[do];W[cp];B[fq];W[fr];B[bp];W[bq];B[pi];W[hr];B[qi];W[bo];B[bn];W[ap];B[cf];W[ce];B[df];W[fd];B[ci];W[ek];B[ei];W[fn];B[hc];W[fb];B[pj];W[qd];B[qc];W[pe];B[od];W[rc];B[rd];W[qe];B[rb];W[nf];B[no];W[md];B[mc];W[ld];B[mh];W[qo];B[rp];W[nm];B[lm];W[nk];B[ol];W[om];B[pl];W[nl];B[pg];W[oe];B[nd];W[ne];B[lk];W[mj];B[ki];W[oo];B[np];W[lh];B[mi];W[kl];B[lj];W[ll];B[km];W[oh];B[oi];W[ml];B[jm];W[jl];B[il];W[ik];B[hk];W[hj];B[ij];W[jk];B[hl];W[jj];B[ii];W[ji];B[en];W[gj];B[hh];W[jh];B[fm];W[gm];B[fl];W[fk];B[dl];W[gh];B[ec];W[ed];B[gg];W[hg];B[fh];W[gi];B[gk];W[fg];B[gf];W[ff];B[fc];W[ge];B[eb];W[dk];B[fj];W[di];B[fi];W[hf];B[dh];W[cm];B[cn];W[bm];B[an];W[go];B[dm];W[el];B[em];W[gl];B[hm];W[gn];B[am];W[eo];B[al];W[bk]C[])</gibodata>
</gibo>