<?xml version="1.0" encoding="UTF-8"?>
<gibo>
	<gseq>19408</gseq><!-- 기보 시퀀스 -->
	<playdate>2009-07-04</playdate>	<!-- 대국일자 (YYYYMMDD)-->
	<kind>0</kind>	<!-- 구분(1:프로기보, 2:한게임기보) -->
	<title>
				
				[2009 한국바둑리그] 4R 3G 2국
				
			
	</title> <!-- 기보 제목(기전이름/상태 입력 상태에 따라 가공하여 보냄) -->
	<playerbseq>47</playerbseq>		<!-- 흑대국자 시퀀스 (=badukpeople.seq)-->
	<playerbname>조한승</playerbname>		<!-- 흑대국자 이름 (=badukpeople.namekorean)-->
	<playerbgrade>9단</playerbgrade>	<!-- 흑대국자 단수 (기보 입력당시의 단수)-->
	<playerbimg>
		http://badukwww.hangame.com/2008baduk/pro_photo/korea/pro_photo183.jpg
		
	</playerbimg>		<!-- 흑대국자 썸네일(입력 안된 경우 노이미지 URL로 보냄) -->
	<playerwseq>51</playerwseq>		<!-- 백대국자 시퀀스 (=badukpeople.seq)-->
	<playerwname>박정상</playerwname>		<!-- 백대국자 이름 (=badukpeople.namekorean)-->
	<playerwgrade>9단</playerwgrade>	<!-- 백대국자 단수 (기보 입력당시의 단수)-->
	<playerwimg>
		http://badukwww.hangame.com/2008baduk/pro_photo/pro_photo085.jpg
		
	</playerwimg>		<!-- 백대국자 썸네일(입력 안된 경우 노이미지 URL로 보냄)-->
	<winplayerseq>51</winplayerseq>	<!-- 승자 시퀀스 (=badukpeople.seq)-->
	<defeatplayerseq>47</defeatplayerseq>	<!-- 패자 시퀀스 (=badukpeople.seq)-->
	<extra>6.5</extra>			<!-- 덤-->
	<gomi>호선</gomi>			<!-- 치수-->
	<limittime>30초 10회</limittime>		<!-- 제한시간-->
	<place>한국기원 바둑TV 스튜디오</place>			<!-- 대국장소-->
	<result>백 반집승</result>	<!-- 결과(ex: 흑 불계승)-->
	<readnum>1050</readnum>		<!-- 조회수-->
	<gibodata>(;AP[PureMorph:1.0]CA[ISO-2022-KR]FF[4]GM[1]ST[2]SZ[19]GN[]PC[http://www.hangame.com/]DT[]TS[]TF[]TM[0분30초10회]RE[백 0.5집 승]HA[호선 - 6집 반 공제]HH[1]PW[[p]박정상]PB[[p]조한승]WR[209]BR[209]ZC[]ZT[]AN[]HC[0]VW[aa:ss]QT[60]QC[5]QF[0]N[Title]C[Summary]QK[DMessage];B[pd]QM[0]N[정답도]C[--]QA[];W[dp];B[fq];W[cn];B[qp];W[dd];B[dr];W[op];B[oq];W[pp];B[pq];W[qo];B[nq];W[np];B[mp];W[qq];B[rp];W[qr];B[rq];W[mq];B[lq];W[rr];B[ro];W[mr];B[nr];W[lr];B[pr];W[qn];B[rn];W[kq];B[lp];W[on];B[kp];W[jq];B[jp];W[iq];B[ip];W[gr];B[qm];W[pm];B[ql];W[pk];B[ms];W[ks];B[cq];W[hp];B[ho];W[gp];B[nm];W[pl];B[no];W[oo];B[nn];W[nk];B[mk];W[mj];B[lk];W[nl];B[ml];W[qf];B[nc];W[lj];B[kk];W[rd];B[kj];W[lc];B[qc];W[of];B[fc];W[rc];B[cf];W[df];B[dg];W[ef];B[ce];W[cd];B[eg];W[ec];B[gd];W[fg];B[ff];W[de];B[gf];W[cg];B[ch];W[bg];B[bh];W[be];B[ei];W[me];B[lb];W[mb];B[ld];W[nb];B[md];W[oc];B[od];W[mc];B[nd];W[kd];B[ob];W[jc];B[le];W[jf];B[nf];W[og];B[ke];W[je];B[kb];W[kc];B[id];W[ic];B[rb];W[hc];B[qk];W[qj];B[rj];W[os];B[ps];W[ns];B[or];W[ns];B[rs];W[sr];B[qs];W[rk];B[pn];W[rm];B[po];W[qn];B[qo];W[rl];B[qn];W[qi];B[eb];W[gb];B[fb];W[dk];B[cb];W[bc];B[gc];W[ha];B[ek];W[el];B[fk];W[dj];B[di];W[cp];B[fr];W[bq];B[gq];W[hq];B[br];W[dq];B[cr];W[om];B[fl];W[go];B[hn];W[em];B[re];W[sb];B[qe];W[qb];B[lh];W[sn];B[sq];W[ni];B[ag];W[bf];B[ig];W[gm];B[il];W[hf];B[hg];W[hm];B[im];W[in];B[io];W[bj];B[kg];W[rf];B[pb];W[ra];B[sf];W[sg];B[se];W[rh];B[sm];W[sl];B[hr];W[ir];B[gs];W[ej];B[fj];W[fm];B[hl];W[mm];B[lm];W[bp];B[cj];W[ck];B[bi];W[ci];B[ng];W[nh];B[hd];W[jd];B[mh];W[jg];B[jh];W[bb];B[cj];W[aj];B[ai];W[ci];B[fp];W[fo];B[cj];W[gl];B[gk];W[ci];B[nj];W[oj];B[cj];W[so];B[ss];W[ci];B[dc];W[ed];B[if];W[oe];B[ne];W[pe];B[qd];W[cj];B[sd];W[sc];B[fe];W[li];B[ki];W[ar];B[ba];W[cc];B[db];W[is];B[hs];W[eq];B[er];W[fi];B[fh];W[gi];B[hk];W[dh];B[eh];W[ib];B[mi];W[nj];B[gn];W[kf];B[lf];W[ie];B[he];W[ls];B[fn];W[en];B[fa];W[ga];B[ep];W[eo];B[na];W[ma];B[oa];W[qa];B[bs];W[af];B[gg];W[ah];B[dh];W[ab];B[sp];W[ri];B[sm];W[sn];B[so];W[sj];B[sm];W[ag];B[sn];W[aq];B[pc];W[aa];B[ca];W[ms];B[os];W[pa];B[as];W[ee];B[fd])</gibodata>
</gibo>