<?xml version="1.0" encoding="UTF-8"?>
<gibo>
	<gseq>20703</gseq><!-- 기보 시퀀스 -->
	<playdate>2010-02-04</playdate>	<!-- 대국일자 (YYYYMMDD)-->
	<kind>0</kind>	<!-- 구분(1:프로기보, 2:한게임기보) -->
	<title>
				
				[제2회 비씨카드배] 32강전 7국
				
			
	</title> <!-- 기보 제목(기전이름/상태 입력 상태에 따라 가공하여 보냄) -->
	<playerbseq>36</playerbseq>		<!-- 흑대국자 시퀀스 (=badukpeople.seq)-->
	<playerbname>유창혁</playerbname>		<!-- 흑대국자 이름 (=badukpeople.namekorean)-->
	<playerbgrade>9단</playerbgrade>	<!-- 흑대국자 단수 (기보 입력당시의 단수)-->
	<playerbimg>
		http://badukwww.hangame.com/2008baduk/pro_photo/pro_photo129.jpg
		
	</playerbimg>		<!-- 흑대국자 썸네일(입력 안된 경우 노이미지 URL로 보냄) -->
	<playerwseq>372</playerwseq>		<!-- 백대국자 시퀀스 (=badukpeople.seq)-->
	<playerwname>야마다 기미오 </playerwname>		<!-- 백대국자 이름 (=badukpeople.namekorean)-->
	<playerwgrade>9단</playerwgrade>	<!-- 백대국자 단수 (기보 입력당시의 단수)-->
	<playerwimg>
		http://badukwww.hangame.com/2008baduk/pro_photo/japan/pro_photo107.jpg
		
	</playerwimg>		<!-- 백대국자 썸네일(입력 안된 경우 노이미지 URL로 보냄)-->
	<winplayerseq>36</winplayerseq>	<!-- 승자 시퀀스 (=badukpeople.seq)-->
	<defeatplayerseq>372</defeatplayerseq>	<!-- 패자 시퀀스 (=badukpeople.seq)-->
	<extra>6.5</extra>			<!-- 덤-->
	<gomi>호선</gomi>			<!-- 치수-->
	<limittime>2시간 60초 3회</limittime>		<!-- 제한시간-->
	<place>한국기원 바둑TV 스튜디오</place>			<!-- 대국장소-->
	<result>흑 불계승</result>	<!-- 결과(ex: 흑 불계승)-->
	<readnum>5305</readnum>		<!-- 조회수-->
	<gibodata>(;AP[PureMorph:1.0]CA[ISO-2022-KR]FF[4]GM[1]ST[2]SZ[19]GN[]PC[http://baduk.hangame.com/]DT[]TS[]TF[]TM[2시간60초3회]RE[흑 불계승]HA[호선 - 6집 반 공제]HH[1]PW[[p]야마다]PB[[p]유창혁]WR[209]BR[209]ZC[3]ZT[60]AN[]HC[0]VW[aa:ss]QT[60]QC[3]QF[0]N[Title]C[Summary]QK[DefaultMessage];B[qd]QM[0]N[정답도]C[--]QA[];W[dc];B[pp];W[dq];B[ce];W[od];B[oc];W[nc];B[pc];W[dh];B[cn];W[dk];B[dp];W[ep];B[cq];W[cr];B[cp];W[er];B[eo];W[fp];B[df];W[ee];B[dd];W[ec];B[cc];W[cb];B[ed];W[fd];B[fc];W[bc];B[cd];W[fb];B[bb];W[db];B[ff];W[fe];B[ef];W[nd];B[gc];W[hd];B[gb];W[ba];B[fa];W[ab];B[hf];W[he];B[jc];W[je];B[if];W[jd];B[kc];W[le];B[eb];W[fh];B[ih];W[qe];B[re];W[pd];B[qc];W[qf];B[rf];W[qh];B[bk];W[kh];B[ij];W[cg];B[qg];W[pg];B[rg];W[ph];B[ei];W[eh];B[cj];W[gj];B[il];W[kj];B[ej];W[gl];B[kg];W[jg];B[jh];W[jf];B[hh];W[ji];B[hj];W[ci];B[bi];W[fi];B[dj];W[hk];B[ik];W[gn];B[kl];W[mk];B[jo];W[mm];B[mp];W[qn];B[nl];W[ml];B[pn];W[pm];B[on];W[qp];B[qq];W[qo];B[pq];W[pl];B[rh];W[ri];B[rj];W[qi];B[iq];W[em];B[en];W[gm];B[fk];W[gk];B[ho];W[go];B[gq];W[dm];B[cm];W[bq];B[bp];W[br];B[gp];W[fo];B[si];W[ln];B[ko];W[cl];B[bl];W[qk];B[nm];W[nk];B[rp];W[ro];B[rq];W[jm];B[im]C[])</gibodata>
</gibo>