<?xml version="1.0" encoding="UTF-8"?>
<gibo>
	<gseq>22912</gseq><!-- 기보 시퀀스 -->
	<playdate>2011-01-18</playdate>	<!-- 대국일자 (YYYYMMDD)-->
	<kind>0</kind>	<!-- 구분(1:프로기보, 2:한게임기보) -->
	<title>
				
				[제12회 농심신라면배] 11국
				
			
	</title> <!-- 기보 제목(기전이름/상태 입력 상태에 따라 가공하여 보냄) -->
	<playerbseq>312</playerbseq>		<!-- 흑대국자 시퀀스 (=badukpeople.seq)-->
	<playerbname>저우루이양</playerbname>		<!-- 흑대국자 이름 (=badukpeople.namekorean)-->
	<playerbgrade>5단</playerbgrade>	<!-- 흑대국자 단수 (기보 입력당시의 단수)-->
	<playerbimg>
		http://badukwww.hangame.com/2008baduk/pro_photo/pro_photo223.jpg
		
	</playerbimg>		<!-- 흑대국자 썸네일(입력 안된 경우 노이미지 URL로 보냄) -->
	<playerwseq>49</playerwseq>		<!-- 백대국자 시퀀스 (=badukpeople.seq)-->
	<playerwname>최철한</playerwname>		<!-- 백대국자 이름 (=badukpeople.namekorean)-->
	<playerwgrade>9단</playerwgrade>	<!-- 백대국자 단수 (기보 입력당시의 단수)-->
	<playerwimg>
		http://badukwww.hangame.com/2008baduk/pro_photo/pro_photo200.jpg
		
	</playerwimg>		<!-- 백대국자 썸네일(입력 안된 경우 노이미지 URL로 보냄)-->
	<winplayerseq>49</winplayerseq>	<!-- 승자 시퀀스 (=badukpeople.seq)-->
	<defeatplayerseq>312</defeatplayerseq>	<!-- 패자 시퀀스 (=badukpeople.seq)-->
	<extra>6.5</extra>			<!-- 덤-->
	<gomi>호선</gomi>			<!-- 치수-->
	<limittime>1시간 60초 1회</limittime>		<!-- 제한시간-->
	<place>부산 농심호텔</place>			<!-- 대국장소-->
	<result>백 불계승</result>	<!-- 결과(ex: 흑 불계승)-->
	<readnum>6508</readnum>		<!-- 조회수-->
	<gibodata>(;AP[PureMorph:1.0]CA[ISO-2022-KR]FF[4]GM[1]ST[2]SZ[19]GN[]PC[http://baduk.hangame.com/]DT[]TS[]TF[]TM[1시간60초5회]RE[백 불계승]HA[호선 - 6집 반 공제]HH[1]PW[p)최철한]PB[p)저우루이양]WR[201]BR[201]ZC[5]ZT[60]AN[]HC[0]VW[aa:ss]QT[60]QC[5]QF[0]N[Title]C[Summary]QK[DefaultMessage];B[pd]QM[0]N[정답도]C[--]QA[];W[dd];B[pq];W[dq];B[co];W[cj];B[gp];W[ep];B[cl];W[ip];B[gn];W[en];B[dk];W[dj];B[fk];W[dm];B[cm];W[ek];B[el];W[ej];B[em];W[cp];B[gr];W[dn];B[dl];W[cn];B[kp];W[gl];B[fl];W[il];B[in];W[gm];B[fn];W[gj];B[fj];W[fi];B[gi];W[hj];B[fh];W[ei];B[fm];W[jo];B[jm];W[ko];B[lp];W[lo];B[mp];W[lm];B[jl];W[lk];B[kk];W[lj];B[gh];W[ih];B[dg];W[cg];B[ch];W[dh];B[eh];W[bh];B[cf];W[ci];B[bg];W[ch];B[ef];W[ji];B[gk];W[hk];B[hi];W[ij];B[iq];W[bf];B[be];W[ag];B[hp];W[fd];B[ce];W[bc];B[ge];W[fe];B[ff];W[de];B[gd];W[df];B[fc];W[hf];B[dc];W[ec];B[eb];W[ed];B[gf];W[jd];B[id];W[fb];B[gc];W[db];B[je];W[ke];B[jf];W[kf];B[kd];W[ld];B[jc];W[kg];B[lc];W[md];B[pf];W[mc];B[qi];W[io];B[hn];W[mo];B[np];W[lb];B[jg];W[jh];B[kc];W[pb];B[nm];W[on];B[om];W[pm];B[pl];W[ql];B[pk];W[pn];B[qk];W[qp];B[qq];W[rq];B[rr];W[ro];B[sq];W[rl];B[lh];W[kh];B[mf];W[oe];B[od];W[ne];B[pe];W[nb];B[er];W[dr];B[kj];W[li];B[mh];W[nk];B[nj];W[qc];B[jj];W[ii];B[rd];W[ng];B[mg];W[kl];B[ml];W[ll];B[nf];W[gb];B[bn];W[bo];B[rb];W[fq];B[ao];W[bp];B[kb];W[rc];B[sc];W[me];B[qb];W[jq];B[ir];W[jp];B[jk];W[ki];B[kr];W[jr];B[js];W[kq];B[lq];W[pc];B[oc];W[ob];B[pp];W[mk];B[ok];W[rp];B[rk];W[qd];B[re];W[qe];B[qf];W[sb];B[sa];W[qa];B[la];W[pa];B[mb];W[nn];B[sl];W[rm];B[hb];W[fr];B[fs];W[bm];B[bl];W[an];B[ds];W[cs];B[es];W[cr];B[mm];W[sm])</gibodata>
</gibo>