<?xml version="1.0" encoding="UTF-8"?>
<gibo>
	<gseq>30030</gseq><!-- 기보 시퀀스 -->
	<playdate>2014-04-25</playdate>	<!-- 대국일자 (YYYYMMDD)-->
	<kind>0</kind>	<!-- 구분(1:프로기보, 2:한게임기보) -->
	<title>
				
				[을조리그] 4라운드
				
			
	</title> <!-- 기보 제목(기전이름/상태 입력 상태에 따라 가공하여 보냄) -->
	<playerbseq>38</playerbseq>		<!-- 흑대국자 시퀀스 (=badukpeople.seq)-->
	<playerbname>이창호</playerbname>		<!-- 흑대국자 이름 (=badukpeople.namekorean)-->
	<playerbgrade>9단</playerbgrade>	<!-- 흑대국자 단수 (기보 입력당시의 단수)-->
	<playerbimg>
		http://badukwww.hangame.com/2008baduk/pro_photo/pro_photo163.jpg
		
	</playerbimg>		<!-- 흑대국자 썸네일(입력 안된 경우 노이미지 URL로 보냄) -->
	<playerwseq>332</playerwseq>		<!-- 백대국자 시퀀스 (=badukpeople.seq)-->
	<playerwname>주위엔하오</playerwname>		<!-- 백대국자 이름 (=badukpeople.namekorean)-->
	<playerwgrade>3단</playerwgrade>	<!-- 백대국자 단수 (기보 입력당시의 단수)-->
	<playerwimg>
		
		http://images.hangame.co.kr/hangame/renewal_2007/baduk/common/noimage_player120x97.gif
	</playerwimg>		<!-- 백대국자 썸네일(입력 안된 경우 노이미지 URL로 보냄)-->
	<winplayerseq>332</winplayerseq>	<!-- 승자 시퀀스 (=badukpeople.seq)-->
	<defeatplayerseq>38</defeatplayerseq>	<!-- 패자 시퀀스 (=badukpeople.seq)-->
	<extra>7.5</extra>			<!-- 덤-->
	<gomi>호선</gomi>			<!-- 치수-->
	<limittime>2시간 60초 5회</limittime>		<!-- 제한시간-->
	<place>-</place>			<!-- 대국장소-->
	<result>백 1.5집 승</result>	<!-- 결과(ex: 흑 불계승)-->
	<readnum>429</readnum>		<!-- 조회수-->
	<gibodata>(;FF[4]GM[1]SZ[19]TM[120시간60초5회]RE[백 1.5집 승]HA[호선 - 7집 반 공제]PB[수순중계4]BR[201]PW[수순중계3]WR[201]QF[0];B[qd];W[dp];B[dc];W[ce];B[pq];W[od];B[oc];W[nc];B[pc];W[nd];B[qf];W[jc];B[cd];W[de];B[fc];W[po];B[mq];W[cj];B[qm];W[on];B[fq];W[dq];B[ip];W[fp];B[cl];W[ek];B[co];W[cp];B[em];W[ck];B[gm];W[gp];B[qp];W[io];B[jp];W[jo];B[ko];W[kp];B[lo];W[jm];B[fk];W[fj];B[gk];W[el];B[fm];W[lm];B[kq];W[pl];B[gj];W[fi];B[gi];W[gh];B[hh];W[hg];B[dl];W[gg];B[be];W[bf];B[bd];W[ih];B[jj];W[ho];B[ki];W[dn];B[dm];W[cn];B[mi];W[oi];B[kl];W[jl];B[hi];W[qo];B[qi];W[og];B[km];W[oq];B[or];W[op];B[gq];W[kk];B[kn];W[jk];B[hp];W[fo];B[jn];W[in];B[lk];W[kj];B[lj];W[qg];B[ji];W[rf];B[pk];W[ql];B[ol];W[ok];B[pm];W[om];B[nl];W[rl];B[oj];W[pj];B[nk];W[qe];B[qk];W[rk];B[rj];W[rm];B[rd];W[nb];B[ob];W[pd];B[qb];W[er];B[im];W[hm];B[il];W[hc];B[bg];W[cg];B[af];W[cf];B[qr];W[kg];B[jg];W[jf];B[lg];W[lf];B[kh];W[kf];B[bm];W[bn];B[ro];W[rn];B[an];W[ao];B[am];W[do];B[gc];W[hd];B[fe];W[hs];B[hr];W[pi];B[qj];W[bh];B[bo];W[bp];B[na];W[ma];B[oa];W[ib];B[gb];W[fs];B[is];W[rp];B[rq];W[so];B[pf];W[pe];B[mf];W[me];B[mg];W[nf];B[re];W[rh];B[gn];W[go];B[sf];W[rg];B[bo];W[ap];B[ja];W[kb];B[ia];W[gs];B[ir];W[pp];B[qq];W[nq];B[nr];W[ff];B[hb];W[ha];B[ge];W[mp];B[lp];W[ig];B[dk];W[dj];B[hn];W[nm];B[he];W[ie];B[ag];W[dd];B[ec];W[ah];B[ae];W[ka];B[ch];W[bi];B[bk];W[jb];B[bj];W[ci];B[fl];W[ej];B[no];W[ml];B[ni];W[np];B[mo];W[ga];B[fa];W[ia];B[ng];W[pg];B[eq];W[aj];B[dr];W[cr];B[ak];W[cm];B[bl];W[mk];B[fr];W[ds];B[gr];W[es];B[oh];W[ph];B[nh];W[sg];B[se];W[si];B[sj];W[ri];B[jh];W[sk];B[nj];W[ea];B[fb];W[cc];B[bc];W[cb];B[bb];W[db];B[sq];W[ii];B[ij];W[ee];B[sp];W[gd];B[fd];W[hf];B[eb];W[ro];B[da];W[ai];B[ep];W[eo];B[gf];W[oo];B[mn];W[mm];B[ll];W[ef];B[ca];W[ed];B[mj];W[fn];B[ok];W[en];B[qh];W[nn];B[ln])</gibodata>
</gibo>