<?xml version="1.0" encoding="UTF-8"?>
<gibo>
	<gseq>31806</gseq><!-- 기보 시퀀스 -->
	<playdate>2015-01-17</playdate>	<!-- 대국일자 (YYYYMMDD)-->
	<kind>0</kind>	<!-- 구분(1:프로기보, 2:한게임기보) -->
	<title>
				
				[여자바둑리그] 1R 2G 3국
				
			
	</title> <!-- 기보 제목(기전이름/상태 입력 상태에 따라 가공하여 보냄) -->
	<playerbseq>66</playerbseq>		<!-- 흑대국자 시퀀스 (=badukpeople.seq)-->
	<playerbname>박지은</playerbname>		<!-- 흑대국자 이름 (=badukpeople.namekorean)-->
	<playerbgrade>9단</playerbgrade>	<!-- 흑대국자 단수 (기보 입력당시의 단수)-->
	<playerbimg>
		http://badukwww.hangame.com/2008baduk/pro_photo/korea/pro_photo089.jpg
		
	</playerbimg>		<!-- 흑대국자 썸네일(입력 안된 경우 노이미지 URL로 보냄) -->
	<playerwseq>1396</playerwseq>		<!-- 백대국자 시퀀스 (=badukpeople.seq)-->
	<playerwname>송혜령</playerwname>		<!-- 백대국자 이름 (=badukpeople.namekorean)-->
	<playerwgrade>초단</playerwgrade>	<!-- 백대국자 단수 (기보 입력당시의 단수)-->
	<playerwimg>
		
		http://images.hangame.co.kr/hangame/renewal_2007/baduk/common/noimage_player120x97.gif
	</playerwimg>		<!-- 백대국자 썸네일(입력 안된 경우 노이미지 URL로 보냄)-->
	<winplayerseq>1396</winplayerseq>	<!-- 승자 시퀀스 (=badukpeople.seq)-->
	<defeatplayerseq>66</defeatplayerseq>	<!-- 패자 시퀀스 (=badukpeople.seq)-->
	<extra>6.5</extra>			<!-- 덤-->
	<gomi>호선</gomi>			<!-- 치수-->
	<limittime>10분 40초 3회</limittime>		<!-- 제한시간-->
	<place>한국기원</place>			<!-- 대국장소-->
	<result>백 1.5집 승</result>	<!-- 결과(ex: 흑 불계승)-->
	<readnum>559</readnum>		<!-- 조회수-->
	<gibodata>(;FF[4]GM[1]SZ[19]TM[10시간40초3회]RE[백 1.5집 승]HA[호선 - 6집 반 공제]PB[수순중계4]BR[201]PW[수순중계3]WR[201]QF[0];B[pd];W[dd];B[pq];W[dq];B[qo];W[kq];B[cf];W[fc];B[do];W[co];B[cn];W[cp];B[dn];W[ep];B[dj];W[qf];B[qe];W[pf];B[nc];W[pj];B[qh];W[ph];B[rf];W[rg];B[re];W[di];B[cj];W[df];B[dg];W[ce];B[ef];W[de];B[mq];W[cg];B[ch];W[bf];B[rh];W[qg];B[sg];W[qi];B[oi];W[ri];B[sh];W[pi];B[ql];W[nf];B[hp];W[lc];B[ld];W[kc];B[md];W[je];B[og];W[of];B[lf];W[mh];B[ko];W[hr];B[gq];W[lp];B[gr];W[mp];B[nq];W[mn];B[lh];W[mi];B[he];W[hc];B[id];W[ke];B[ic];W[jc];B[mf];W[ib];B[ol];W[jo];B[er];W[dr];B[jp];W[kp];B[kn];W[ip];B[io];W[jq];B[in];W[ml];B[nk];W[oj];B[nj];W[ni];B[mg];W[ng];B[li];W[kl];B[jn];W[pm];B[pl];W[lm];B[no];W[np];B[op];W[oo];B[on];W[nn];B[lk];W[il];B[jk];W[jl];B[ir];W[iq];B[hq];W[gl];B[gn];W[hj];B[dh];W[hg];B[hb];W[gb];B[bo];W[bp];B[bn];W[br];B[hi];W[mo];B[om];W[ii];B[ih];W[gi];B[hh];W[gh];B[jh];W[fj];B[gg];W[jr];B[hs];W[bh];B[bi];W[ei];B[ah];W[bg];B[ci];W[rk];B[kk];W[lr];B[ll];W[km];B[mr];W[el];B[ek];W[fk];B[ik];W[hk];B[hm];W[hl];B[mb];W[dl];B[cl];W[rm];B[rn];W[od];B[oc];W[pp];B[oq];W[po];B[qp];W[pe];B[qc];W[gf];B[fg];W[hf];B[fh];W[ej];B[dk];W[fm];B[fn];W[dm];B[if];W[fe];B[ie];W[cm];B[bm];W[bl];B[ck];W[sf];B[se];W[rl];B[mj];W[oh];B[eq];W[dp];B[pn];W[si];B[sf];W[fp];B[ij];W[ig];B[jf];W[jg];B[kd];W[jd];B[kf];W[kh];B[ji];W[kg];B[gd];W[gc];B[lb];W[kb];B[fd];W[ee];B[qm];W[fq];B[fr];W[la];B[ma];W[ka];B[ki];W[mc];B[nb];W[nd];B[ne];W[oe];B[lg];W[eh];B[eg];W[no];B[en];W[js];B[ls];W[ks];B[ms];W[lq];B[ed];W[ec];B[qk];W[qj];B[sm];W[sl];B[sn];W[go];B[ho];W[is];B[em];W[fl];B[hr];W[ag];B[ai];W[fi];B[bk];W[ao];B[an];W[ap];B[ds];W[cs];B[es];W[jp];B[me];W[ge];B[hd];W[ha];B[nm];W[mm])</gibodata>
</gibo>