<?xml version="1.0" encoding="UTF-8"?>
<gibo>
	<gseq>32734</gseq><!-- 기보 시퀀스 -->
	<playdate>2015-05-18</playdate>	<!-- 대국일자 (YYYYMMDD)-->
	<kind>0</kind>	<!-- 구분(1:프로기보, 2:한게임기보) -->
	<title>
				
				
				[일본 기성전(碁聖戰)] 도전자결정전
			
	</title> <!-- 기보 제목(기전이름/상태 입력 상태에 따라 가공하여 보냄) -->
	<playerbseq>422</playerbseq>		<!-- 흑대국자 시퀀스 (=badukpeople.seq)-->
	<playerbname>고노 린</playerbname>		<!-- 흑대국자 이름 (=badukpeople.namekorean)-->
	<playerbgrade>9단</playerbgrade>	<!-- 흑대국자 단수 (기보 입력당시의 단수)-->
	<playerbimg>
		http://badukwww.hangame.com/2008baduk/pro_photo/japan/pro_photo012.jpg
		
	</playerbimg>		<!-- 흑대국자 썸네일(입력 안된 경우 노이미지 URL로 보냄) -->
	<playerwseq>411</playerwseq>		<!-- 백대국자 시퀀스 (=badukpeople.seq)-->
	<playerwname>야마시타 게이고</playerwname>		<!-- 백대국자 이름 (=badukpeople.namekorean)-->
	<playerwgrade>9단</playerwgrade>	<!-- 백대국자 단수 (기보 입력당시의 단수)-->
	<playerwimg>
		http://badukwww.hangame.com/2008baduk/pro_photo/japan/pro_photo114.jpg
		
	</playerwimg>		<!-- 백대국자 썸네일(입력 안된 경우 노이미지 URL로 보냄)-->
	<winplayerseq>411</winplayerseq>	<!-- 승자 시퀀스 (=badukpeople.seq)-->
	<defeatplayerseq>422</defeatplayerseq>	<!-- 패자 시퀀스 (=badukpeople.seq)-->
	<extra>6.5</extra>			<!-- 덤-->
	<gomi>호선</gomi>			<!-- 치수-->
	<limittime>3시간 60초 5회</limittime>		<!-- 제한시간-->
	<place>일본기원</place>			<!-- 대국장소-->
	<result>백 불계승</result>	<!-- 결과(ex: 흑 불계승)-->
	<readnum>258</readnum>		<!-- 조회수-->
	<gibodata>(;FF[4]GM[1]SZ[19]TM[180시간60초5회]RE[백 불계승]HA[호선 - 6집 반 공제]PB[수순중계4]BR[201]PW[수순중계3]WR[201]QF[0];B[qd];W[dc];B[pq];W[dp];B[ce];W[oc];B[hc];W[cd];B[ed];W[be];B[bf];W[de];B[cf];W[ee];B[kc];W[ci];B[fc];W[dd];B[bd];W[bc];B[ae];W[bh];B[dg];W[gd];B[cb];W[bb];B[eb];W[db];B[fg];W[jd];B[jc];W[hd];B[gc];W[fi];B[hg];W[hi];B[kd];W[je];B[jg];W[ke];B[le];W[lf];B[kf];W[gf];B[gg];W[eh];B[eg];W[me];B[ld];W[hf];B[lg];W[mf];B[pe];W[mg];B[lh];W[mh];B[li];W[pg];B[mi];W[qf];B[pc];W[od];B[qe];W[lb];B[da];W[ba];B[md];W[oe];B[ob];W[nb];B[pb];W[nc];B[kb];W[pj];B[rf];W[pf];B[rg];W[pm];B[cn];W[cl];B[fp];W[co];B[dn];W[eo];B[dl];W[dk];B[el];W[en];B[gj];W[gl];B[ek];W[fj];B[ck];W[bk];B[dj];W[bl];B[fm];W[bn];B[gm];W[go];B[im];W[di];B[gi];W[gk];B[hj];W[ij];B[hk];W[hl];B[il];W[ik];B[gh];W[hm];B[hn];W[fk];B[gn];W[in];B[ho];W[jn];B[km];W[hq];B[ip];W[kn];B[kl];W[iq];B[jp];W[lm];B[ll];W[fo];B[jq];W[hp];B[ln];W[lo];B[mn];W[ko];B[io];W[mo];B[lq];W[ec];B[fb];W[nn];B[mm];W[np];B[nr];W[pp];B[oq];W[qp];B[dm];W[fr];B[ph];W[oh];B[oi];W[pi];B[qh];W[ni];B[oj];W[nj];B[ok];W[nk];B[pk];W[ml];B[ql];W[lk];B[kk];W[jm];B[jl];W[of];B[nm];W[om];B[on];W[kj];B[nl];W[lj];B[ol];W[ji];B[ih];W[ii];B[ng];W[nh];B[mk];W[mj];B[fd];W[fe];B[mc];W[ki];B[jk];W[nd];B[oo];W[mb];B[rm];W[ka];B[ja];W[la];B[ib];W[id])</gibodata>
</gibo>