<?xml version="1.0" encoding="UTF-8"?>
<gibo>
	<gseq>37657</gseq><!-- 기보 시퀀스 -->
	<playdate>2016-06-16</playdate>	<!-- 대국일자 (YYYYMMDD)-->
	<kind>0</kind>	<!-- 구분(1:프로기보, 2:한게임기보) -->
	<title>
				
				
				[2016 KB국민은행 바둑리그] 4R 1G 4국
			
	</title> <!-- 기보 제목(기전이름/상태 입력 상태에 따라 가공하여 보냄) -->
	<playerbseq>158</playerbseq>		<!-- 흑대국자 시퀀스 (=badukpeople.seq)-->
	<playerbname>김지석</playerbname>		<!-- 흑대국자 이름 (=badukpeople.namekorean)-->
	<playerbgrade>9단</playerbgrade>	<!-- 흑대국자 단수 (기보 입력당시의 단수)-->
	<playerbimg>
		http://badukwww.hangame.com/2008baduk/pro_photo/pro_photo052.jpg
		
	</playerbimg>		<!-- 흑대국자 썸네일(입력 안된 경우 노이미지 URL로 보냄) -->
	<playerwseq>224</playerwseq>		<!-- 백대국자 시퀀스 (=badukpeople.seq)-->
	<playerwname>강유택</playerwname>		<!-- 백대국자 이름 (=badukpeople.namekorean)-->
	<playerwgrade>7단</playerwgrade>	<!-- 백대국자 단수 (기보 입력당시의 단수)-->
	<playerwimg>
		http://badukwww.hangame.com/2008baduk/pro_photo/pro_photo004.jpg
		
	</playerwimg>		<!-- 백대국자 썸네일(입력 안된 경우 노이미지 URL로 보냄)-->
	<winplayerseq>158</winplayerseq>	<!-- 승자 시퀀스 (=badukpeople.seq)-->
	<defeatplayerseq>224</defeatplayerseq>	<!-- 패자 시퀀스 (=badukpeople.seq)-->
	<extra>6.5</extra>			<!-- 덤-->
	<gomi>호선</gomi>			<!-- 치수-->
	<limittime>10분 40초 5회</limittime>		<!-- 제한시간-->
	<place>한국기원</place>			<!-- 대국장소-->
	<result>흑 1.5집 승</result>	<!-- 결과(ex: 흑 불계승)-->
	<readnum>96</readnum>		<!-- 조회수-->
	<gibodata>(;FF[4]GM[1]SZ[19]TM[10시간40초5회]RE[흑 1.5집 승]HA[호선 - 6집 반 공제]PB[수순중계4]BR[201]PW[수순중계3]WR[201]QF[0];B[pd];W[dd];B[qp];W[dp];B[fq];W[cn];B[lq];W[qf];B[pi];W[qc];B[qd];W[pc];B[od];W[rd];B[re];W[rc];B[qe];W[nc];B[fo];W[dr];B[pn];W[gp];B[fp];W[hn];B[dm];W[dn];B[fm];W[ip];B[hl];W[lo];B[nq];W[jm];B[jk];W[ll];B[lj];W[qq];B[pp];W[rp];B[ro];W[rr];B[me];W[nl];B[mm];W[ml];B[kn];W[ln];B[km];W[lm];B[kl];W[ko];B[jn];W[jo];B[in];W[or];B[oq];W[nr];B[sp];W[pq];B[mq];W[pl];B[rq];W[sr];B[ql];W[pk];B[qk];W[pj];B[qj];W[oi];B[ph];W[en];B[fn];W[fc];B[nj];W[oj];B[jq];W[oh];B[om];W[pm];B[nm];W[ol];B[mh];W[iq];B[nk];W[pg];B[og];W[qm];B[ri];W[mi];B[li];W[no];B[oo];W[rl];B[rk];W[hr];B[er];W[mg];B[nh];W[ni];B[ng];W[jr];B[kr];W[ce];B[js];W[np];B[op];W[gq];B[ir];W[mj];B[lk];W[mk];B[cl];W[fr];B[fs];W[gr];B[cg];W[eg];B[eq];W[cq];B[ci];W[gg];B[hc];W[nd];B[ne];W[lc];B[he];W[ge];B[gd];W[fe];B[jc];W[hf];B[cc];W[dc];B[be];W[bd];B[bf];W[kc];B[je];W[se];B[sf];W[sd];B[rf];W[bc];B[ho];W[hp];B[bm];W[bn];B[ig];W[ke];B[oc];W[ob];B[mc];W[mb];B[md];W[nb];B[if];W[kf];B[kg];W[em];B[an];W[ao];B[am];W[bp];B[gb];W[fb];B[kb];W[lb];B[hi];W[dk];B[ck];W[lg];B[kh];W[dj];B[cr];W[br];B[mr];W[cj];B[bj];W[ns];B[io];W[jp];B[rm];W[gk];B[gj];W[fj];B[hk];W[gi];B[hj];W[le];B[fa];W[ea];B[ga];W[eb];B[ib];W[hh];B[ih];W[fk];B[hg];W[gh];B[qn];W[ka];B[jb];W[di];B[bh];W[go];B[gn];W[cm];B[bl];W[dg];B[gf];W[ff];B[dl];W[jf];B[jd];W[el];B[cf];W[df];B[gl];W[dh];B[ch];W[gc];B[ja];W[la];B[ms];W[pr];B[eo];W[do];B[es];W[dq];B[ds];W[cs];B[ad];W[ac];B[ae];W[fd];B[hd];W[jg];B[jh];W[sq];B[rp];W[lh];B[mf];W[lf];B[of];W[fl];B[on];W[lp];B[kq];W[mp];B[hf];W[mn];B[is];W[kd];B[hm])</gibodata>
</gibo>