<?xml version="1.0" encoding="UTF-8"?>
<gibo>
	<gseq>38180</gseq><!-- 기보 시퀀스 -->
	<playdate>2016-07-12</playdate>	<!-- 대국일자 (YYYYMMDD)-->
	<kind>0</kind>	<!-- 구분(1:프로기보, 2:한게임기보) -->
	<title>
				
				
				[중국 여자 갑조리그] 8R
			
	</title> <!-- 기보 제목(기전이름/상태 입력 상태에 따라 가공하여 보냄) -->
	<playerbseq>1289</playerbseq>		<!-- 흑대국자 시퀀스 (=badukpeople.seq)-->
	<playerbname>왕천싱</playerbname>		<!-- 흑대국자 이름 (=badukpeople.namekorean)-->
	<playerbgrade>5단</playerbgrade>	<!-- 흑대국자 단수 (기보 입력당시의 단수)-->
	<playerbimg>
		
		http://images.hangame.co.kr/hangame/renewal_2007/baduk/common/noimage_player120x97.gif
	</playerbimg>		<!-- 흑대국자 썸네일(입력 안된 경우 노이미지 URL로 보냄) -->
	<playerwseq>354</playerwseq>		<!-- 백대국자 시퀀스 (=badukpeople.seq)-->
	<playerwname>쑹룽후이</playerwname>		<!-- 백대국자 이름 (=badukpeople.namekorean)-->
	<playerwgrade>5단</playerwgrade>	<!-- 백대국자 단수 (기보 입력당시의 단수)-->
	<playerwimg>
		http://badukwww.hangame.com/2008baduk/pro_photo/pro_photo226.jpg
		
	</playerwimg>		<!-- 백대국자 썸네일(입력 안된 경우 노이미지 URL로 보냄)-->
	<winplayerseq>354</winplayerseq>	<!-- 승자 시퀀스 (=badukpeople.seq)-->
	<defeatplayerseq>1289</defeatplayerseq>	<!-- 패자 시퀀스 (=badukpeople.seq)-->
	<extra>7.5</extra>			<!-- 덤-->
	<gomi>호선</gomi>			<!-- 치수-->
	<limittime>2시간 60초 5회</limittime>		<!-- 제한시간-->
	<place>-</place>			<!-- 대국장소-->
	<result>백 불계승</result>	<!-- 결과(ex: 흑 불계승)-->
	<readnum>69</readnum>		<!-- 조회수-->
	<gibodata>(;FF[4]GM[1]SZ[19]TM[120시간60초5회]RE[백 불계승]HA[호선 - 7집 반 공제]PB[수순중계4]BR[201]PW[수순중계3]WR[201]QF[0];B[pd];W[dd];B[qp];W[eq];B[cp];W[oq];B[lp];W[on];B[qm];W[ip];B[lm];W[po];B[qo];W[pl];B[pm];W[om];B[ol];W[mm];B[ln];W[nl];B[ok];W[ll];B[kl];W[lk];B[jm];W[kk];B[jk];W[jj];B[ik];W[ij];B[hk];W[qf];B[pj];W[nc];B[pf];W[pg];B[of];W[qd];B[qc];W[qe];B[pb];W[qi];B[og];W[ph];B[oh];W[rk];B[pi];W[rh];B[kd];W[ql];B[rm];W[qr];B[rl];W[qk];B[rr];W[le];B[ld];W[pe];B[oe];W[od];B[pc];W[ne];B[lg];W[nf];B[mh];W[lf];B[kg];W[jf];B[kf];W[ke];B[je];W[jd];B[ie];W[jc];B[nb];W[mb];B[oc];W[md];B[rd];W[re];B[se];W[qg];B[kj];W[lq];B[kq];W[mp];B[kp];W[rq];B[op];W[pr];B[pp];W[mn];B[rp];W[sr];B[pn];W[jh];B[lj];W[oo];B[np];W[nk];B[mo];W[mj];B[mk];W[ml];B[li];W[oj];B[oi];W[pk];B[hf];W[mq];B[nd];W[mc];B[dg];W[no];B[rn];W[gd];B[do];W[fg];B[fe];W[ef];B[fd];W[gi];B[hh];W[hj];B[jg];W[gk];B[hm];W[df];B[dj];W[gm];B[gn];W[fm];B[ho];W[cl];B[cg];W[cf];B[fj];W[gj];B[ck];W[dl];B[bl];W[bm];B[bk];W[eo];B[en];W[fn];B[fo];W[ep];B[dn];W[gp];B[go];W[cq];B[bq];W[br];B[gh];W[cm];B[cr];W[dq];B[bo];W[aq];B[ap];W[bp];B[am];W[an];B[bq];W[io];B[in];W[bp];B[dc];W[ao];B[cc];W[eh];B[ei];W[cd];B[bc];W[ec];B[fc];W[eb];B[fb];W[di];B[ej];W[ci];B[bi];W[ed];B[bg];W[fa];B[hb];W[bd];B[db];W[bb];B[ab];W[ba];B[ad];W[ae];B[ga];W[ea];B[be];W[ac];B[mf];W[me];B[ad];W[kn];B[km];W[ac];B[jb];W[bf];B[kb];W[eg];B[dh];W[ag];B[ah];W[af];B[cj];W[rc];B[rb];W[sd];B[hp];W[na];B[ob];W[kc];B[mg];W[hq];B[iq];W[hc];B[ib];W[sb];B[ra];W[od];B[oa];W[ir];B[jq];W[ih];B[ig];W[hr];B[lr];W[mr];B[nq];W[nr];B[el];W[em];B[gl];W[fl];B[hl];W[fk];B[ek];W[lo];B[ko];W[dm];B[pq];W[or];B[rj];W[qj];B[sk];W[al];B[jr];W[ni];B[ak];W[nh];B[ng];W[mi];B[gg];W[ff];B[gf];W[ls];B[kr];W[ee];B[am];W[lb];B[nd];W[ge];B[gb];W[od];B[hd];W[qa])</gibodata>
</gibo>