<?xml version="1.0" encoding="UTF-8"?>
<gibo>
	<gseq>38988</gseq><!-- 기보 시퀀스 -->
	<playdate>2016-09-06</playdate>	<!-- 대국일자 (YYYYMMDD)-->
	<kind>0</kind>	<!-- 구분(1:프로기보, 2:한게임기보) -->
	<title>
				
				[삼성화재배] 32강 1회전
				
			
	</title> <!-- 기보 제목(기전이름/상태 입력 상태에 따라 가공하여 보냄) -->
	<playerbseq>836</playerbseq>		<!-- 흑대국자 시퀀스 (=badukpeople.seq)-->
	<playerbname>궈원차오</playerbname>		<!-- 흑대국자 이름 (=badukpeople.namekorean)-->
	<playerbgrade>5단</playerbgrade>	<!-- 흑대국자 단수 (기보 입력당시의 단수)-->
	<playerbimg>
		
		http://images.hangame.co.kr/hangame/renewal_2007/baduk/common/noimage_player120x97.gif
	</playerbimg>		<!-- 흑대국자 썸네일(입력 안된 경우 노이미지 URL로 보냄) -->
	<playerwseq>86</playerwseq>		<!-- 백대국자 시퀀스 (=badukpeople.seq)-->
	<playerwname>강동윤</playerwname>		<!-- 백대국자 이름 (=badukpeople.namekorean)-->
	<playerwgrade>9단</playerwgrade>	<!-- 백대국자 단수 (기보 입력당시의 단수)-->
	<playerwimg>
		http://badukwww.hangame.com/2008baduk/pro_photo/pro_photo001.jpg
		
	</playerwimg>		<!-- 백대국자 썸네일(입력 안된 경우 노이미지 URL로 보냄)-->
	<winplayerseq>86</winplayerseq>	<!-- 승자 시퀀스 (=badukpeople.seq)-->
	<defeatplayerseq>836</defeatplayerseq>	<!-- 패자 시퀀스 (=badukpeople.seq)-->
	<extra>6.5</extra>			<!-- 덤-->
	<gomi>호선</gomi>			<!-- 치수-->
	<limittime>2시간 60초 5회</limittime>		<!-- 제한시간-->
	<place>삼성화재 글로벌캠퍼스</place>			<!-- 대국장소-->
	<result>백 불계승</result>	<!-- 결과(ex: 흑 불계승)-->
	<readnum>284</readnum>		<!-- 조회수-->
	<gibodata>(;FF[4]GM[1]SZ[19]TM[120시간60초5회]RE[백 불계승]HA[호선 - 6집 반 공제]PB[수순중계4]BR[201]PW[수순중계3]WR[201]QF[0];B[pd];W[dc];B[pq];W[dq];B[qo];W[oq];B[op];W[nq];B[pp];W[kq];B[de];W[cg];B[cc];W[gc];B[dd];W[db];B[fd];W[hc];B[dh];W[dg];B[eg];W[ch];B[di];W[ci];B[dj];W[ck];B[jc];W[ef];B[fg];W[ge];B[gd];W[hd];B[fe];W[kd];B[jd];W[je];B[lc];W[ke];B[mc];W[dk];B[ib];W[hf];B[gf];W[he];B[df];W[fp];B[jo];W[mo];B[jq];W[jp];B[kp];W[ip];B[lq];W[kr];B[lr];W[lp];B[ko];W[jr];B[mp];W[lo];B[np];W[ls];B[mq];W[lm];B[cq];W[cp];B[dp];W[do];B[io];W[hp];B[jl];W[lk];B[kj];W[kk];B[jk];W[jj];B[lj];W[mj];B[mk];W[km];B[ml];W[ij];B[kh];W[jm];B[im];W[mm];B[ih];W[lh];B[mi];W[nj];B[ni];W[oj];B[ol];W[oi];B[li];W[in];B[ng];W[pg];B[hl];W[hm];B[hj];W[gg];B[ff];W[fb];B[cb];W[hb];B[ik];W[pl];B[pm];W[nf];B[pk];W[og];B[qe];W[il];B[nh];W[oe];B[nd];W[rf];B[qf];W[qg];B[re];W[gl];B[im];W[od];B[oc];W[il];B[bp];W[ep];B[im];W[pc];B[mf];W[ob];B[nc];W[qc];B[ne];W[of];B[lf];W[jg];B[ig];W[if];B[rg];W[rh];B[sf];W[ql];B[ec];W[eb];B[ri];W[om];B[qh];W[ok];B[cj];W[bj];B[hn];W[il];B[bk];W[hk];B[bi];W[bl];B[aj];W[rb];B[sc];W[sb];B[pb];W[nb];B[mb];W[pa];B[co];W[cr];B[dp];W[bq];B[gk];W[kl];B[cp];W[br];B[cm];W[ld])</gibodata>
</gibo>