<?xml version="1.0" encoding="UTF-8"?>
<gibo>
	<gseq>40051</gseq><!-- 기보 시퀀스 -->
	<playdate>2016-12-08</playdate>	<!-- 대국일자 (YYYYMMDD)-->
	<kind>0</kind>	<!-- 구분(1:프로기보, 2:한게임기보) -->
	<title>
				
				
				[일본 기성전(棋聖戰)] 예선
			
	</title> <!-- 기보 제목(기전이름/상태 입력 상태에 따라 가공하여 보냄) -->
	<playerbseq>1594</playerbseq>		<!-- 흑대국자 시퀀스 (=badukpeople.seq)-->
	<playerbname>츠네이시 다카시</playerbname>		<!-- 흑대국자 이름 (=badukpeople.namekorean)-->
	<playerbgrade>3단</playerbgrade>	<!-- 흑대국자 단수 (기보 입력당시의 단수)-->
	<playerbimg>
		
		http://images.hangame.co.kr/hangame/renewal_2007/baduk/common/noimage_player120x97.gif
	</playerbimg>		<!-- 흑대국자 썸네일(입력 안된 경우 노이미지 URL로 보냄) -->
	<playerwseq>382</playerwseq>		<!-- 백대국자 시퀀스 (=badukpeople.seq)-->
	<playerwname>고바야시 고이치</playerwname>		<!-- 백대국자 이름 (=badukpeople.namekorean)-->
	<playerwgrade>9단</playerwgrade>	<!-- 백대국자 단수 (기보 입력당시의 단수)-->
	<playerwimg>
		http://badukwww.hangame.com/2008baduk/pro_photo/japan/pro_photo017.jpg
		
	</playerwimg>		<!-- 백대국자 썸네일(입력 안된 경우 노이미지 URL로 보냄)-->
	<winplayerseq>382</winplayerseq>	<!-- 승자 시퀀스 (=badukpeople.seq)-->
	<defeatplayerseq>1594</defeatplayerseq>	<!-- 패자 시퀀스 (=badukpeople.seq)-->
	<extra>6.5</extra>			<!-- 덤-->
	<gomi>호선</gomi>			<!-- 치수-->
	<limittime>3시간 60초 3회</limittime>		<!-- 제한시간-->
	<place>일본기원</place>			<!-- 대국장소-->
	<result>백 4.5집 승</result>	<!-- 결과(ex: 흑 불계승)-->
	<readnum>268</readnum>		<!-- 조회수-->
	<gibodata>(;FF[4]GM[1]SZ[19]TM[180시간60초3회]RE[백 4.5집 승]HA[호선 - 6집 반 공제]PB[수순중계4]BR[201]PW[수순중계3]WR[201]QF[0];B[pd];W[dd];B[qp];W[dq];B[co];W[ck];B[fp];W[ep];B[eo];W[fq];B[gp];W[gq];B[hp];W[hq];B[ip];W[jq];B[ci];W[ek];B[cf];W[ei];B[ef];W[fc];B[bd];W[ic];B[pj];W[oq];B[po];W[qh];B[qi];W[ph];B[nj];W[rd];B[qd];W[ri];B[rj];W[rc];B[qf];W[re];B[rf];W[qe];B[pe];W[pf];B[rh];W[rg];B[pg];W[sf];B[of];W[sh];B[qb];W[rb];B[kc];W[jp];B[cc];W[jn];B[dp];W[eq];B[cq];W[cr];B[bq];W[dc];B[pq];W[np];B[no];W[mo];B[nn];W[je];B[ke];W[kf];B[le];W[cd];B[bb];W[cb];B[bc];W[dg];B[cg];W[ce];B[dh];W[be];B[db];W[eb];B[ca];W[dn];B[do];W[cn];B[br];W[eg];B[eh];W[fg];B[fh];W[df];B[gh];W[gg];B[jd];W[id];B[jf];W[ie];B[mp];W[mq];B[lp];W[lq];B[op];W[nq];B[em];W[cj];B[fj];W[fk];B[gk];W[gl];B[hk];W[bi];B[bh];W[di];B[ch];W[bo];B[en];W[dl];B[dr];W[er];B[cs];W[ln];B[ko];W[jo];B[lm];W[kn];B[mn];W[qc];B[pc];W[kb];B[jb];W[jc];B[lb];W[kd];B[lc];W[lf];B[me];W[jg];B[bj];W[bk];B[ai];W[gn];B[hl];W[gm];B[fl];W[el];B[es];W[fs];B[ds];W[iq];B[or];W[pr];B[qr];W[mk];B[mj];W[kk];B[ml];W[lj];B[nk];W[hi];B[hh];W[ii];B[gj];W[ag];B[jl];W[kl];B[in];W[io];B[jk];W[jj];B[ij];W[ji];B[jm];W[km];B[im];W[fo];B[nr];W[mr];B[pb];W[qg];B[ib];W[hb];B[lo];W[sj];B[rk];W[bp];B[cp];W[ak];B[af];W[bf];B[aj];W[pi];B[qj];W[sk];B[sl];W[si];B[rl];W[ia];B[ka];W[ns];B[ps];W[ll];B[mm];W[ae];B[bg];W[ea];B[da];W[pf];B[qf];W[kp];B[mo];W[mi];B[mg];W[lh];B[mh];W[ni];B[lg];W[kg];B[mf];W[ig];B[ra];W[fm];B[ej];W[dj];B[ih];W[jh];B[hg];W[hf];B[nh];W[oh];B[dm];W[cm];B[oj];W[oi];B[bn];W[bm];B[og];W[hj];B[ik];W[ad];B[ac];W[ap];B[an];W[am];B[aq];W[ao];B[ld];W[sb];B[lk];W[jd];B[mk])</gibodata>
</gibo>