<?xml version="1.0" encoding="UTF-8"?>
<gibo>
	<gseq>4320</gseq><!-- 기보 시퀀스 -->
	<playdate>2006-11-28</playdate>	<!-- 대국일자 (YYYYMMDD)-->
	<kind>0</kind>	<!-- 구분(1:프로기보, 2:한게임기보) -->
	<title>
				
				
				[루키스 프로리그] 리그 46국
			
	</title> <!-- 기보 제목(기전이름/상태 입력 상태에 따라 가공하여 보냄) -->
	<playerbseq>203</playerbseq>		<!-- 흑대국자 시퀀스 (=badukpeople.seq)-->
	<playerbname>김수용</playerbname>		<!-- 흑대국자 이름 (=badukpeople.namekorean)-->
	<playerbgrade>2단</playerbgrade>	<!-- 흑대국자 단수 (기보 입력당시의 단수)-->
	<playerbimg>
		
		http://images.hangame.co.kr/hangame/renewal_2007/baduk/common/noimage_player120x97.gif
	</playerbimg>		<!-- 흑대국자 썸네일(입력 안된 경우 노이미지 URL로 보냄) -->
	<playerwseq>207</playerwseq>		<!-- 백대국자 시퀀스 (=badukpeople.seq)-->
	<playerwname>박승화</playerwname>		<!-- 백대국자 이름 (=badukpeople.namekorean)-->
	<playerwgrade>2단</playerwgrade>	<!-- 백대국자 단수 (기보 입력당시의 단수)-->
	<playerwimg>
		
		http://images.hangame.co.kr/hangame/renewal_2007/baduk/common/noimage_player120x97.gif
	</playerwimg>		<!-- 백대국자 썸네일(입력 안된 경우 노이미지 URL로 보냄)-->
	<winplayerseq>203</winplayerseq>	<!-- 승자 시퀀스 (=badukpeople.seq)-->
	<defeatplayerseq>207</defeatplayerseq>	<!-- 패자 시퀀스 (=badukpeople.seq)-->
	<extra>6.5</extra>			<!-- 덤-->
	<gomi>호선</gomi>			<!-- 치수-->
	<limittime>10분, 30초 3회</limittime>		<!-- 제한시간-->
	<place>한게임 바둑 대국실</place>			<!-- 대국장소-->
	<result>흑 불계승</result>	<!-- 결과(ex: 흑 불계승)-->
	<readnum>395</readnum>		<!-- 조회수-->
	<gibodata>(;AP[HangameBadookEditor:1.0]CA[ISO-2022-KR]FF[4]GM[1]ST[2]SZ[19]GN[AutoConversion];B[qd];W[dd];B[pq];W[dp];B[fc];W[hc];B[oc];W[po];B[qo];W[qn];B[qp];W[rd];B[re];W[qe];B[pe];W[qf];B[rf];W[qg];B[rg];W[qh];B[qc];W[pn];B[nq];W[qj];B[cc];W[dc];B[cd];W[de];B[db];W[eb];B[cb];W[ec];B[cf];W[kc];B[fq];W[cn];B[dr];W[cq];B[hp];W[ch];B[cg];W[dh];B[mn];W[kn];B[om];W[pp];B[qq];W[pl];B[in];W[kp];B[km];W[mp];B[np];W[iq];B[hq];W[ip];B[lq];W[kq];B[lr]C[];W[jr];B[hr];W[mo];B[jn];W[no];B[ko];W[lp];B[dm];W[cm];B[dk];W[eg];B[rh];W[ri];B[pi];W[qi];B[cl];W[cr];B[dn];W[do];B[fn];W[el];B[ek];W[bl];B[dl];W[bk];B[fh];W[gf];B[ih];W[kj];B[kh];W[mj];B[ie];W[he];B[ic];W[ib];B[id];W[jb];B[hd];W[gd];B[hg];W[ij];B[ol];W[ni];B[ea];W[fa];B[da];W[fd];B[hj];W[nb];B[nc];W[mb];B[ik];W[jk];B[il];W[rn];B[pm];W[ql];B[ro];W[ok];B[nk];W[ml];B[mm];W[nl];B[on];W[oo];B[oh];W[nh];B[og];W[oi];B[ng];W[ke];B[mc];W[pf];B[oe];W[rc];B[rb];W[of];B[nf];W[ne];B[pb];W[me];B[lg];W[lc];B[hf];W[ge];B[eq];W[jf];B[if];W[jg];B[jh];W[fi];B[ei];W[gh];B[ii];W[fj];B[eh];W[gg];B[di];W[bh];B[jj];W[gj];B[fk];W[gk];B[gl];W[af];B[be];W[fo];B[go];W[eo];B[pk];W[oj];B[ph];W[pj];B[cs];W[bs];B[ds];W[dq];B[er];W[br];B[lk];W[ll];B[kk];W[kl];B[mk];W[ae];B[ad];W[bg];B[bf];W[ag];B[ab]PW[박승화]WR[초단]WT[]PB[김수용]BR[초단]BT[]HA[]KM[6.5]RE[흑 불계승]DT[2006.11.28]OT[]PC[한게임 바둑 대국실]RO[]EV[제1회 루키스 프로리그 리그 46국]US[]AN[]CP[]SO[]GC[]TM[600]TS[00:00:00]TF[00:00:00]ZT[30]ZC[3])</gibodata>
</gibo>