<?xml version="1.0" encoding="UTF-8"?>
<gibo>
	<gseq>5015</gseq><!-- 기보 시퀀스 -->
	<playdate>2007-05-13</playdate>	<!-- 대국일자 (YYYYMMDD)-->
	<kind>0</kind>	<!-- 구분(1:프로기보, 2:한게임기보) -->
	<title>
				
				
				[2007 한국바둑리그] 2R 2G 5국
			
	</title> <!-- 기보 제목(기전이름/상태 입력 상태에 따라 가공하여 보냄) -->
	<playerbseq>85</playerbseq>		<!-- 흑대국자 시퀀스 (=badukpeople.seq)-->
	<playerbname>김주호</playerbname>		<!-- 흑대국자 이름 (=badukpeople.namekorean)-->
	<playerbgrade>7단</playerbgrade>	<!-- 흑대국자 단수 (기보 입력당시의 단수)-->
	<playerbimg>
		
		http://images.hangame.co.kr/hangame/renewal_2007/baduk/common/noimage_player120x97.gif
	</playerbimg>		<!-- 흑대국자 썸네일(입력 안된 경우 노이미지 URL로 보냄) -->
	<playerwseq>135</playerwseq>		<!-- 백대국자 시퀀스 (=badukpeople.seq)-->
	<playerwname>최원용</playerwname>		<!-- 백대국자 이름 (=badukpeople.namekorean)-->
	<playerwgrade>5단</playerwgrade>	<!-- 백대국자 단수 (기보 입력당시의 단수)-->
	<playerwimg>
		
		http://images.hangame.co.kr/hangame/renewal_2007/baduk/common/noimage_player120x97.gif
	</playerwimg>		<!-- 백대국자 썸네일(입력 안된 경우 노이미지 URL로 보냄)-->
	<winplayerseq>85</winplayerseq>	<!-- 승자 시퀀스 (=badukpeople.seq)-->
	<defeatplayerseq>135</defeatplayerseq>	<!-- 패자 시퀀스 (=badukpeople.seq)-->
	<extra>6.5</extra>			<!-- 덤-->
	<gomi>호선</gomi>			<!-- 치수-->
	<limittime>10분, 30초 3회</limittime>		<!-- 제한시간-->
	<place>바둑TV 스튜디오</place>			<!-- 대국장소-->
	<result>흑 불계승</result>	<!-- 결과(ex: 흑 불계승)-->
	<readnum>833</readnum>		<!-- 조회수-->
	<gibodata>(;AP[HangameBadookEditor:1.0]CA[ISO-2022-KR]FF[4]GM[1]ST[2]SZ[19]GN[AutoConversion];B[pd];W[dd];B[qp];W[dq];B[co];W[ck];B[hp];W[fp];B[cq];W[cr];B[br];W[cp];B[bq];W[dp];B[bp];W[jq];B[io];W[mq];B[oq];W[ko];B[lp];W[lq];B[kp];W[jp];B[jo];W[kn];B[mp];W[kq];B[np];W[hq];B[jm];W[qj];B[ql];W[qf];B[mc];W[ph];B[re];W[nc];B[oc];W[nd];B[nb];W[rf];B[md];W[fc];B[be];W[bd];B[ce];W[cd];B[ci];W[ol];B[pk];W[km];B[kl];W[ll];B[lm];W[ln];B[mm];W[mn];B[jl];W[nm];B[ml];W[oo];B[pn];W[on];B[pj];W[qo];B[rp];W[pm];B[qi];W[pp];B[pq];W[ro];B[so];W[sn];B[sp];W[pi];B[rj];W[nj];B[lk];W[ri];B[nk];W[ok];B[oj];W[ni];B[qk];W[qh];B[rh];W[qj];B[oi];W[oh];B[qi];W[mj];B[nl];W[qj];B[pl];W[om];B[rn];W[rm];B[sm];W[qn];B[sn];W[rk];B[rl];W[sj];B[qm];W[bn];B[bo];W[dr];B[dn];W[ek];B[dl];W[cm];B[dm];W[dk];B[bj];W[bk];B[ei];W[fm];B[cn];W[bm];B[fn];W[gn];B[fo];W[go];B[gp];W[mk];B[ll];W[gl];B[gq]C[])</gibodata>
</gibo>